{"state":{"name":"","banner":null,"stages":[{"id":"w1","title":"World Building","status":"In Progress","layout":{"top":[{"id":"n1","type":"note","val":"Setting details..."}],"mid":[{"id":"i1","type":"image","val":"","caption":"Map"}],"bot":[{"id":"f1","type":"file","val":"","name":"Wiki"}]}},{"id":"w2","title":"Beats","status":"Not Started","layout":{"top":[{"id":"b1","type":"note","val":"ACT I"}],"mid":[],"bot":[]}}],"theme":"light","lastUpdated":1767825923320,"initialized":true},"axioms":[{"id":1767825923320,"name":"Writer Nexus Booted","timestamp":"22:45","state":"{\"name\":\"\",\"banner\":null,\"stages\":[{\"id\":\"w1\",\"title\":\"World Building\",\"status\":\"In Progress\",\"layout\":{\"top\":[{\"id\":\"n1\",\"type\":\"note\",\"val\":\"Setting details...\"}],\"mid\":[{\"id\":\"i1\",\"type\":\"image\",\"val\":\"\",\"caption\":\"Map\"}],\"bot\":[{\"id\":\"f1\",\"type\":\"file\",\"val\":\"\",\"name\":\"Wiki\"}]}},{\"id\":\"w2\",\"title\":\"Beats\",\"status\":\"Not Started\",\"layout\":{\"top\":[{\"id\":\"b1\",\"type\":\"note\",\"val\":\"ACT I\"}],\"mid\":[],\"bot\":[]}}],\"theme\":\"light\",\"lastUpdated\":1767825923320,\"initialized\":true}"}],"projectStrata":[{"id":0,"name":"Core Draft","color":"#6366f1"},{"id":1,"name":"Refining","color":"#ec4899"},{"id":2,"name":"Polishing","color":"#f59e0b"}],"historyIndex":0}